ape_trezor/__init__.py
ape_trezor/_cli.py
ape_trezor/accounts.py
ape_trezor/choices.py
ape_trezor/client.py
ape_trezor/exceptions.py
ape_trezor/hdpath.py
ape_trezor/py.typed
ape_trezor/utils.py
ape_trezor/version.py
ape_trezor-0.8.3.dist-info/licenses/LICENSE
ape_trezor-0.8.3.dist-info/METADATA
ape_trezor-0.8.3.dist-info/WHEEL
ape_trezor-0.8.3.dist-info/entry_points.txt
ape_trezor-0.8.3.dist-info/top_level.txt
ape_trezor-0.8.3.dist-info/RECORD
